ollama_rich/__init__.py
ollama_rich/cli.py
ollama_rich/config.py
ollama_rich/ollama_rich.py
ollama_rich/utils.py
ollama_rich-1.0.4.dist-info/licenses/LICENSE
ollama_rich-1.0.4.dist-info/METADATA
ollama_rich-1.0.4.dist-info/WHEEL
ollama_rich-1.0.4.dist-info/entry_points.txt
ollama_rich-1.0.4.dist-info/top_level.txt
ollama_rich-1.0.4.dist-info/RECORD
