Metadata-Version: 2.4
Name: ollama-rich
Version: 1.0.4
Summary: A feature-rich Ollama client with enhanced terminal UI using the Rich library.
Home-page: https://github.com/jakbin/ollama-rich
Author: Jak BIn
License: MIT
Project-URL: Source, https://github.com/jakbin/ollama-rich
Project-URL: Tracker, https://github.com/jakbin/ollama-rich/issues
Classifier: Programming Language :: Python :: 3
Classifier: License :: OSI Approved :: MIT License
Classifier: Operating System :: OS Independent
Requires-Python: >=3.7
License-File: LICENSE
Requires-Dist: appdirs
Requires-Dist: rich
Requires-Dist: ollama
Requires-Dist: pyyaml
Dynamic: author
Dynamic: classifier
Dynamic: description
Dynamic: description-content-type
Dynamic: home-page
Dynamic: license
Dynamic: license-file
Dynamic: project-url
Dynamic: requires-dist
Dynamic: requires-python
Dynamic: summary
